ocr/__init__.py
ocr/api_ppocr_json.py
ocr/engine.py
ocr/engine_ram_optimization.py
ocr/msn.py
ocr/msn_batch_paths.py
ocr/msn_quick.py
ocr/output.py
ocr/output_jsonl.py
ocr/output_md.py
ocr/output_panel.py
ocr/output_separate_txt.py
ocr/output_txt.py
ocr/tbpu/__init__.py
ocr/tbpu/ignore_area.py
ocr/tbpu/merge_line.py
ocr/tbpu/merge_line_h.py
ocr/tbpu/merge_line_h_fuzzy.py
ocr/tbpu/merge_line_h_m_fuzzy.py
ocr/tbpu/merge_line_h_m_left.py
ocr/tbpu/merge_line_h_m_paragraph.py
ocr/tbpu/merge_line_h_m_paragraph_english.py
ocr/tbpu/merge_line_v_lr.py
ocr/tbpu/merge_line_v_rl.py
ocr/tbpu/merge_para.py
ocr/tbpu/merge_para_code.py
ocr/tbpu/tbpu.py
ui/__init__.py
ui/tray.py
ui/widget.py
ui/win_main.py
ui/win_notify.py
ui/win_ocr_language.py
ui/win_screenshot.py
ui/win_select_area.py
ui/win_show_image.py
ui/pmw/PmwBalloon.py
ui/pmw/PmwBase.py
ui/pmw/__init__.py
ui/systray/__init__.py
ui/systray/traybar.py
ui/systray/win32_adapter.py
utils/__init__.py
utils/asset.py
utils/command_arg.py
utils/config.py
utils/data_structure.py
utils/hotkey.py
utils/logger.py
utils/pynput_hotkey.py
utils/startup.py
utils/tool.py
utils/gflags/__init__.py
utils/gflags/_helpers.py
utils/gflags/_helpers_test.py
utils/gflags/argument_parser.py
utils/gflags/exceptions.py
utils/gflags/flag.py
utils/gflags/flags_formatting_test.py
utils/gflags/flags_unicode_literals_test.py
utils/gflags/flagvalues.py
utils/gflags/validators.py
utils/gflags/flags_modules_for_testing/__init__.py
utils/gflags/flags_modules_for_testing/module_bar.py
utils/gflags/flags_modules_for_testing/module_baz.py
utils/gflags/flags_modules_for_testing/module_foo.py
utils/gflags/third_party/__init__.py
utils/gflags/third_party/pep257/__init__.py
Umi_OCR-1.2.1.dist-info/License
Umi_OCR-1.2.1.dist-info/METADATA
Umi_OCR-1.2.1.dist-info/WHEEL
Umi_OCR-1.2.1.dist-info/top_level.txt
Umi_OCR-1.2.1.dist-info/RECORD
